[
  {
    "data": {
      "text": "﻿[Col. 0849B] \n\n[Col. 0849C] \nBeata virgo Ermelindis, ex Ermenoldo patre et Ermesende matre, tam genere quam divitiis spectabilibus, exorta, ab ineunte ætate studuit de virtute in virtutem ascendere, ut Deum deorum in Syon videre mereretur. Quæ cum adhuc parentum in domo puerilis ætatis vinculo teneretur astricta, nichil tamen puerile gerebat in opere, sed quamdam maturitatem morum in gestu intuentibus se præferebat. Declinabat siquidem lasciviam atque consortia coætanearum, in thalamo genetricis suæ residens, psalmosque Davidicos discens. Si quando verbum Dei audisset, memoria sagaci recondebat, sæpiusque ad os reducens, quasi mundum animal, novo semper pietatis affectu ruminabat. Jam tunc suavitatem sponsi prægustabat magno et incomprehensibili modo, desiderioque illius exæstuans, cum sancto David dicebat: “Sitivit anima mea ad Deum fontem vivum, quando veniam et apparebo ante faciem Dei mei?” et iterum: “Sicut cervus desiderat ad fontes aquarum, ita desiderat anima mea ad te, Deus.” \n\n[Col. 0849D]"
    },
    "predictions": [
      {
        "model_version": "gliner2-multi-v1",
        "score": 0.8796500265598297,
        "result": [
          {
            "id": "c5d80a1f",
            "type": "labels",
            "value": {
              "start": 711,
              "end": 717,
              "text": "sponsi",
              "labels": [
                "person"
              ]
            },
            "from_name": "label",
            "to_name": "text",
            "origin": "prediction",
            "score": 0.9609418511390686
          },
          {
            "id": "6bb8cee6",
            "type": "labels",
            "value": {
              "start": 30,
              "end": 52,
              "text": "Beata virgo Ermelindis",
              "labels": [
                "person"
              ]
            },
            "from_name": "label",
            "to_name": "text",
            "origin": "prediction",
            "score": 0.9539441466331482
          },
          {
            "id": "ff188c8c",
            "type": "labels",
            "value": {
              "start": 76,
              "end": 91,
              "text": "Ermesende matre",
              "labels": [
                "person"
              ]
            },
            "from_name": "label",
            "to_name": "text",
            "origin": "prediction",
            "score": 0.9189059734344482
          },
          {
            "id": "95f87de1",
            "type": "labels",
            "value": {
              "start": 57,
              "end": 66,
              "text": "Ermenoldo",
              "labels": [
                "person"
              ]
            },
            "from_name": "label",
            "to_name": "text",
            "origin": "prediction",
            "score": 0.8685514330863953
          },
          {
            "id": "9e13db72",
            "type": "labels",
            "value": {
              "start": 491,
              "end": 501,
              "text": "genetricis",
              "labels": [
                "person"
              ]
            },
            "from_name": "label",
            "to_name": "text",
            "origin": "prediction",
            "score": 0.7432584762573242
          },
          {
            "id": "200884f5",
            "type": "labels",
            "value": {
              "start": 798,
              "end": 810,
              "text": "sancto David",
              "labels": [
                "person"
              ]
            },
            "from_name": "label",
            "to_name": "text",
            "origin": "prediction",
            "score": 0.663409948348999
          },
          {
            "id": "8959e5f2",
            "type": "labels",
            "value": {
              "start": 467,
              "end": 478,
              "text": "coætanearum",
              "labels": [
                "group"
              ]
            },
            "from_name": "label",
            "to_name": "text",
            "origin": "prediction",
            "score": 0.9415356516838074
          },
          {
            "id": "aab30aeb",
            "type": "labels",
            "value": {
              "start": 255,
              "end": 263,
              "text": "parentum",
              "labels": [
                "group"
              ]
            },
            "from_name": "label",
            "to_name": "text",
            "origin": "prediction",
            "score": 0.9370684027671814
          },
          {
            "id": "fbf991d1",
            "type": "labels",
            "value": {
              "start": 527,
              "end": 536,
              "text": "Davidicos",
              "labels": [
                "group"
              ]
            },
            "from_name": "label",
            "to_name": "text",
            "origin": "prediction",
            "score": 0.8530858159065247
          },
          {
            "id": "02368322",
            "type": "labels",
            "value": {
              "start": 457,
              "end": 466,
              "text": "consortia",
              "labels": [
                "group"
              ]
            },
            "from_name": "label",
            "to_name": "text",
            "origin": "prediction",
            "score": 0.6756958961486816
          },
          {
            "id": "824923f7",
            "type": "labels",
            "value": {
              "start": 994,
              "end": 998,
              "text": "Deus",
              "labels": [
                "divine_entity"
              ]
            },
            "from_name": "label",
            "to_name": "text",
            "origin": "prediction",
            "score": 0.9904516935348511
          },
          {
            "id": "5269e71f",
            "type": "labels",
            "value": {
              "start": 899,
              "end": 902,
              "text": "Dei",
              "labels": [
                "divine_entity"
              ]
            },
            "from_name": "label",
            "to_name": "text",
            "origin": "prediction",
            "score": 0.9824181199073792
          },
          {
            "id": "a00de216",
            "type": "labels",
            "value": {
              "start": 563,
              "end": 566,
              "text": "Dei",
              "labels": [
                "divine_entity"
              ]
            },
            "from_name": "label",
            "to_name": "text",
            "origin": "prediction",
            "score": 0.9802781939506531
          },
          {
            "id": "3d2b218a",
            "type": "labels",
            "value": {
              "start": 842,
              "end": 846,
              "text": "Deum",
              "labels": [
                "divine_entity"
              ]
            },
            "from_name": "label",
            "to_name": "text",
            "origin": "prediction",
            "score": 0.9610045552253723
          },
          {
            "id": "78a91255",
            "type": "labels",
            "value": {
              "start": 203,
              "end": 207,
              "text": "Deum",
              "labels": [
                "divine_entity"
              ]
            },
            "from_name": "label",
            "to_name": "text",
            "origin": "prediction",
            "score": 0.9433557391166687
          },
          {
            "id": "e9182f08",
            "type": "labels",
            "value": {
              "start": 805,
              "end": 810,
              "text": "David",
              "labels": [
                "divine_entity"
              ]
            },
            "from_name": "label",
            "to_name": "text",
            "origin": "prediction",
            "score": 0.6001096963882446
          },
          {
            "id": "fa8a12a8",
            "type": "labels",
            "value": {
              "start": 483,
              "end": 490,
              "text": "thalamo",
              "labels": [
                "place"
              ]
            },
            "from_name": "label",
            "to_name": "text",
            "origin": "prediction",
            "score": 0.985414981842041
          },
          {
            "id": "b013b038",
            "type": "labels",
            "value": {
              "start": 218,
              "end": 222,
              "text": "Syon",
              "labels": [
                "place"
              ]
            },
            "from_name": "label",
            "to_name": "text",
            "origin": "prediction",
            "score": 0.9807012677192688
          },
          {
            "id": "7a3fc363",
            "type": "labels",
            "value": {
              "start": 267,
              "end": 271,
              "text": "domo",
              "labels": [
                "place"
              ]
            },
            "from_name": "label",
            "to_name": "text",
            "origin": "prediction",
            "score": 0.9804274439811707
          },
          {
            "id": "274b8953",
            "type": "labels",
            "value": {
              "start": 947,
              "end": 961,
              "text": "fontes aquarum",
              "labels": [
                "place"
              ]
            },
            "from_name": "label",
            "to_name": "text",
            "origin": "prediction",
            "score": 0.6724412441253662
          }
        ]
      }
    ]
  },
  {
    "data": {
      "text": "[2]  Cumque pueritia transisset in adolescentiam, parentibus eam nubere filiosque procreare volentibus, nullatenus consensit, dicens se Christo virginitatem suam devovisse. Arrepto denique ferro, capillos per lacteam cervicem dependentes præscidit; relictoque sæculo et omnibus pompis ejus, Christum, quem sibi sponsum elegerat, per arctam et angustam viam secuta est. Nec retraxit pedem, donec ad bravium perveniret: in memoria semper habens, quid pro nobis fecerit, quidque fuerit passus. Parentes autem illius, nec minis, nec blanditiis propositum ejus immutare valentes, redditus cujusdam villulæ Odunca nomine ad famulatus sui usum unanimiter tradiderunt."
    },
    "predictions": [
      {
        "model_version": "gliner2-multi-v1",
        "score": 0.8025469834154303,
        "result": [
          {
            "id": "c37eaf7f",
            "type": "labels",
            "value": {
              "start": 72,
              "end": 81,
              "text": "filiosque",
              "labels": [
                "person"
              ]
            },
            "from_name": "label",
            "to_name": "text",
            "origin": "prediction",
            "score": 0.7863976359367371
          },
          {
            "id": "36f47fc9",
            "type": "labels",
            "value": {
              "start": 50,
              "end": 60,
              "text": "parentibus",
              "labels": [
                "group"
              ]
            },
            "from_name": "label",
            "to_name": "text",
            "origin": "prediction",
            "score": 0.8587847948074341
          },
          {
            "id": "56fa1d71",
            "type": "labels",
            "value": {
              "start": 491,
              "end": 499,
              "text": "Parentes",
              "labels": [
                "group"
              ]
            },
            "from_name": "label",
            "to_name": "text",
            "origin": "prediction",
            "score": 0.8054870367050171
          },
          {
            "id": "552376dd",
            "type": "labels",
            "value": {
              "start": 453,
              "end": 458,
              "text": "nobis",
              "labels": [
                "group"
              ]
            },
            "from_name": "label",
            "to_name": "text",
            "origin": "prediction",
            "score": 0.682677149772644
          },
          {
            "id": "5dc895d2",
            "type": "labels",
            "value": {
              "start": 575,
              "end": 583,
              "text": "redditus",
              "labels": [
                "object"
              ]
            },
            "from_name": "label",
            "to_name": "text",
            "origin": "prediction",
            "score": 0.799166738986969
          },
          {
            "id": "91fdb0b0",
            "type": "labels",
            "value": {
              "start": 196,
              "end": 204,
              "text": "capillos",
              "labels": [
                "object"
              ]
            },
            "from_name": "label",
            "to_name": "text",
            "origin": "prediction",
            "score": 0.7912936806678772
          },
          {
            "id": "a4fe31c4",
            "type": "labels",
            "value": {
              "start": 189,
              "end": 194,
              "text": "ferro",
              "labels": [
                "object"
              ]
            },
            "from_name": "label",
            "to_name": "text",
            "origin": "prediction",
            "score": 0.7765381932258606
          },
          {
            "id": "d0f78c71",
            "type": "labels",
            "value": {
              "start": 217,
              "end": 225,
              "text": "cervicem",
              "labels": [
                "object"
              ]
            },
            "from_name": "label",
            "to_name": "text",
            "origin": "prediction",
            "score": 0.537275493144989
          },
          {
            "id": "3e54b9ca",
            "type": "labels",
            "value": {
              "start": 291,
              "end": 299,
              "text": "Christum",
              "labels": [
                "divine_entity"
              ]
            },
            "from_name": "label",
            "to_name": "text",
            "origin": "prediction",
            "score": 0.9905545115470886
          },
          {
            "id": "d3ec2fb6",
            "type": "labels",
            "value": {
              "start": 136,
              "end": 143,
              "text": "Christo",
              "labels": [
                "divine_entity"
              ]
            },
            "from_name": "label",
            "to_name": "text",
            "origin": "prediction",
            "score": 0.9873127341270447
          },
          {
            "id": "cafcd678",
            "type": "labels",
            "value": {
              "start": 398,
              "end": 405,
              "text": "bravium",
              "labels": [
                "place"
              ]
            },
            "from_name": "label",
            "to_name": "text",
            "origin": "prediction",
            "score": 0.8125288486480713
          }
        ]
      }
    ]
  },
  {
    "data": {
      "text": "[3]At beata virgo Ermelindis, relicta domo, rebusque parentum postpositis, solitaria incedebat, solicite exquirens locum, ubi soli Deo vacare posset. Venit ergo ad quandam villam, cui præerant duo germani fratres, primo juventutis flore vernantes. Isti necdum legitima contraxerant matrimonia, sed vanitatibus sæculi atque illecebris inserviebant. Ibi ergo venerabilis virgo, aliquandiu commorata, hunc locum \n\n[Col. 0849E] \n\næstimabat a Deo sibi præparatum. Diebus vero ac noctibus frequentabat ecclesiam, nudis pedibus incedens, Domino in holocaustum proprium corpus offerens: humiliabat se servituti subjiciens, nichil de generis nobilitate blandiens. De nobili enim ejus prosapia descendisse dicitur Pippinus, pater sanctæ Gertrudis, cujus meritis B. Ermelindis studuit esse coæqualis. Necdum in tempore illo sanctus Amandus, gubernacula Trajectensis ecclesiæ susceperat, cujus doctrina et institutione multi postea de errore suo ad vias justitiæ redire coacti sunt."
    },
    "predictions": [
      {
        "model_version": "gliner2-multi-v1",
        "score": 0.8624384782531045,
        "result": [
          {
            "id": "1c3ab5ac",
            "type": "labels",
            "value": {
              "start": 6,
              "end": 28,
              "text": "beata virgo Ermelindis",
              "labels": [
                "person"
              ]
            },
            "from_name": "label",
            "to_name": "text",
            "origin": "prediction",
            "score": 0.9697139859199524
          },
          {
            "id": "d4082cb9",
            "type": "labels",
            "value": {
              "start": 704,
              "end": 712,
              "text": "Pippinus",
              "labels": [
                "person"
              ]
            },
            "from_name": "label",
            "to_name": "text",
            "origin": "prediction",
            "score": 0.9590334296226501
          },
          {
            "id": "656d504e",
            "type": "labels",
            "value": {
              "start": 357,
              "end": 374,
              "text": "venerabilis virgo",
              "labels": [
                "person"
              ]
            },
            "from_name": "label",
            "to_name": "text",
            "origin": "prediction",
            "score": 0.9488316178321838
          },
          {
            "id": "8da82606",
            "type": "labels",
            "value": {
              "start": 813,
              "end": 828,
              "text": "sanctus Amandus",
              "labels": [
                "person"
              ]
            },
            "from_name": "label",
            "to_name": "text",
            "origin": "prediction",
            "score": 0.9476925730705261
          },
          {
            "id": "715d71cc",
            "type": "labels",
            "value": {
              "start": 720,
              "end": 736,
              "text": "sanctæ Gertrudis",
              "labels": [
                "person"
              ]
            },
            "from_name": "label",
            "to_name": "text",
            "origin": "prediction",
            "score": 0.9252002835273743
          },
          {
            "id": "46d6e5e4",
            "type": "labels",
            "value": {
              "start": 752,
              "end": 765,
              "text": "B. Ermelindis",
              "labels": [
                "person"
              ]
            },
            "from_name": "label",
            "to_name": "text",
            "origin": "prediction",
            "score": 0.668926477432251
          },
          {
            "id": "fb7fd958",
            "type": "labels",
            "value": {
              "start": 53,
              "end": 61,
              "text": "parentum",
              "labels": [
                "person"
              ]
            },
            "from_name": "label",
            "to_name": "text",
            "origin": "prediction",
            "score": 0.5425701141357422
          },
          {
            "id": "ceb05421",
            "type": "labels",
            "value": {
              "start": 220,
              "end": 230,
              "text": "juventutis",
              "labels": [
                "group"
              ]
            },
            "from_name": "label",
            "to_name": "text",
            "origin": "prediction",
            "score": 0.90826016664505
          },
          {
            "id": "261c99ba",
            "type": "labels",
            "value": {
              "start": 907,
              "end": 912,
              "text": "multi",
              "labels": [
                "group"
              ]
            },
            "from_name": "label",
            "to_name": "text",
            "origin": "prediction",
            "score": 0.751334011554718
          },
          {
            "id": "60cd2f88",
            "type": "labels",
            "value": {
              "start": 193,
              "end": 212,
              "text": "duo germani fratres",
              "labels": [
                "group"
              ]
            },
            "from_name": "label",
            "to_name": "text",
            "origin": "prediction",
            "score": 0.7376990914344788
          },
          {
            "id": "0b2381d3",
            "type": "labels",
            "value": {
              "start": 53,
              "end": 61,
              "text": "parentum",
              "labels": [
                "group"
              ]
            },
            "from_name": "label",
            "to_name": "text",
            "origin": "prediction",
            "score": 0.5041652917861938
          },
          {
            "id": "69c44aa6",
            "type": "labels",
            "value": {
              "start": 562,
              "end": 568,
              "text": "corpus",
              "labels": [
                "object"
              ]
            },
            "from_name": "label",
            "to_name": "text",
            "origin": "prediction",
            "score": 0.9089555144309998
          },
          {
            "id": "9f7dbd21",
            "type": "labels",
            "value": {
              "start": 44,
              "end": 52,
              "text": "rebusque",
              "labels": [
                "object"
              ]
            },
            "from_name": "label",
            "to_name": "text",
            "origin": "prediction",
            "score": 0.5465442538261414
          },
          {
            "id": "64edcfcf",
            "type": "labels",
            "value": {
              "start": 438,
              "end": 441,
              "text": "Deo",
              "labels": [
                "divine_entity"
              ]
            },
            "from_name": "label",
            "to_name": "text",
            "origin": "prediction",
            "score": 0.9955573678016663
          },
          {
            "id": "4d657e44",
            "type": "labels",
            "value": {
              "start": 531,
              "end": 537,
              "text": "Domino",
              "labels": [
                "divine_entity"
              ]
            },
            "from_name": "label",
            "to_name": "text",
            "origin": "prediction",
            "score": 0.9951882362365723
          },
          {
            "id": "05b26f02",
            "type": "labels",
            "value": {
              "start": 131,
              "end": 134,
              "text": "Deo",
              "labels": [
                "divine_entity"
              ]
            },
            "from_name": "label",
            "to_name": "text",
            "origin": "prediction",
            "score": 0.994471549987793
          },
          {
            "id": "695f16da",
            "type": "labels",
            "value": {
              "start": 38,
              "end": 42,
              "text": "domo",
              "labels": [
                "place"
              ]
            },
            "from_name": "label",
            "to_name": "text",
            "origin": "prediction",
            "score": 0.976740300655365
          },
          {
            "id": "4a677949",
            "type": "labels",
            "value": {
              "start": 172,
              "end": 178,
              "text": "villam",
              "labels": [
                "place"
              ]
            },
            "from_name": "label",
            "to_name": "text",
            "origin": "prediction",
            "score": 0.9662389159202576
          },
          {
            "id": "a219b889",
            "type": "labels",
            "value": {
              "start": 403,
              "end": 408,
              "text": "locum",
              "labels": [
                "place"
              ]
            },
            "from_name": "label",
            "to_name": "text",
            "origin": "prediction",
            "score": 0.931323230266571
          },
          {
            "id": "490baa2b",
            "type": "labels",
            "value": {
              "start": 115,
              "end": 120,
              "text": "locum",
              "labels": [
                "place"
              ]
            },
            "from_name": "label",
            "to_name": "text",
            "origin": "prediction",
            "score": 0.9202508926391602
          },
          {
            "id": "07abb255",
            "type": "labels",
            "value": {
              "start": 496,
              "end": 505,
              "text": "ecclesiam",
              "labels": [
                "institution"
              ]
            },
            "from_name": "label",
            "to_name": "text",
            "origin": "prediction",
            "score": 0.9825411438941956
          },
          {
            "id": "a0e5754f",
            "type": "labels",
            "value": {
              "start": 855,
              "end": 863,
              "text": "ecclesiæ",
              "labels": [
                "institution"
              ]
            },
            "from_name": "label",
            "to_name": "text",
            "origin": "prediction",
            "score": 0.8924080729484558
          }
        ]
      }
    ]
  },
  {
    "data": {
      "text": "[4]  Fuit igitur hæc virgo suæ generationis singularis lucerna, inter quos enituit candore virtutum, sicut lilium inter spinas. Nec defuit ei temptatio inimici. Antiquus enim hostis, calcaneo illius insidians, moliebatur effundere oleum, quod adhuc in vase fictili conservabat. Siquidem prædicti fratres, introitum illius et egressum sæpius considerantes, exarserunt in concupiscentiam ejus; ignorans alter cogitationem alterius. Uterque tamen observabat tempus et horam, qua eam solam deprehendere potuisset, quatenus decore illius suam libidinem satiaret. \n\n[Col. 0849F] \n\nSed cum tempus congruum malitiæ suæ implendæ minime reperirent, interius cæco cruciabantur amore. Quid tamen agerent? Non enim sine gravi scandalo totius oppidi vim inferre poterant tantæ opinionis virgini. Unus autem ex eis, quem flamma libidinis amplius exurebat, expetiit custodem ecclesiæ, dona maxima repromittens, si per eum consensum virginis habere potuisset. Illi enim sæpius atque familiarius loquebatur; per eum singulis noctibus ad ecclesiam habebat accessum; quamvis sub ovina pelle sanctitatem virginis tamdiu latere non potuisset. Ille vero, de consensu virginis omnino desperans, (sciebat enim mentem illius solidatam esse et in Christo fundatam,) rapiendam potius fore sub conticinio noctis juveni suadebat. Hac enim hora, gustato paulisper somno, solita erat venire ad ecclesiam, offerens seipsam hostiam vivam, sanctam, Deo placentem. Et quid agis, o humana malicia? Non est sapiencia, non est prudencia, non est consilium contra Dominum. \n\n\n[Col. 0850A]"
    },
    "predictions": [
      {
        "model_version": "gliner2-multi-v1",
        "score": 0.90129746110351,
        "result": [
          {
            "id": "cb3197e9",
            "type": "labels",
            "value": {
              "start": 773,
              "end": 780,
              "text": "virgini",
              "labels": [
                "person"
              ]
            },
            "from_name": "label",
            "to_name": "text",
            "origin": "prediction",
            "score": 0.9892405867576599
          },
          {
            "id": "001d69c2",
            "type": "labels",
            "value": {
              "start": 1083,
              "end": 1091,
              "text": "virginis",
              "labels": [
                "person"
              ]
            },
            "from_name": "label",
            "to_name": "text",
            "origin": "prediction",
            "score": 0.988543689250946
          },
          {
            "id": "af97c4ff",
            "type": "labels",
            "value": {
              "start": 1144,
              "end": 1152,
              "text": "virginis",
              "labels": [
                "person"
              ]
            },
            "from_name": "label",
            "to_name": "text",
            "origin": "prediction",
            "score": 0.9869158267974854
          },
          {
            "id": "e09e53de",
            "type": "labels",
            "value": {
              "start": 916,
              "end": 924,
              "text": "virginis",
              "labels": [
                "person"
              ]
            },
            "from_name": "label",
            "to_name": "text",
            "origin": "prediction",
            "score": 0.9868985414505005
          },
          {
            "id": "eb6ab1bf",
            "type": "labels",
            "value": {
              "start": 21,
              "end": 26,
              "text": "virgo",
              "labels": [
                "person"
              ]
            },
            "from_name": "label",
            "to_name": "text",
            "origin": "prediction",
            "score": 0.9850426912307739
          },
          {
            "id": "30ee3412",
            "type": "labels",
            "value": {
              "start": 1283,
              "end": 1289,
              "text": "juveni",
              "labels": [
                "person"
              ]
            },
            "from_name": "label",
            "to_name": "text",
            "origin": "prediction",
            "score": 0.9647859334945679
          },
          {
            "id": "1af259b4",
            "type": "labels",
            "value": {
              "start": 175,
              "end": 181,
              "text": "hostis",
              "labels": [
                "person"
              ]
            },
            "from_name": "label",
            "to_name": "text",
            "origin": "prediction",
            "score": 0.9219720363616943
          },
          {
            "id": "528ab68c",
            "type": "labels",
            "value": {
              "start": 850,
              "end": 858,
              "text": "custodem",
              "labels": [
                "person"
              ]
            },
            "from_name": "label",
            "to_name": "text",
            "origin": "prediction",
            "score": 0.8217108845710754
          },
          {
            "id": "34e0ddd4",
            "type": "labels",
            "value": {
              "start": 296,
              "end": 303,
              "text": "fratres",
              "labels": [
                "group"
              ]
            },
            "from_name": "label",
            "to_name": "text",
            "origin": "prediction",
            "score": 0.976439893245697
          },
          {
            "id": "b163a0bd",
            "type": "labels",
            "value": {
              "start": 430,
              "end": 437,
              "text": "Uterque",
              "labels": [
                "group"
              ]
            },
            "from_name": "label",
            "to_name": "text",
            "origin": "prediction",
            "score": 0.7658501863479614
          },
          {
            "id": "050fc0ca",
            "type": "labels",
            "value": {
              "start": 152,
              "end": 159,
              "text": "inimici",
              "labels": [
                "group"
              ]
            },
            "from_name": "label",
            "to_name": "text",
            "origin": "prediction",
            "score": 0.5868246555328369
          },
          {
            "id": "7afdd13e",
            "type": "labels",
            "value": {
              "start": 231,
              "end": 236,
              "text": "oleum",
              "labels": [
                "object"
              ]
            },
            "from_name": "label",
            "to_name": "text",
            "origin": "prediction",
            "score": 0.9752620458602905
          },
          {
            "id": "bda8294b",
            "type": "labels",
            "value": {
              "start": 1390,
              "end": 1397,
              "text": "hostiam",
              "labels": [
                "object"
              ]
            },
            "from_name": "label",
            "to_name": "text",
            "origin": "prediction",
            "score": 0.9248717427253723
          },
          {
            "id": "e78561e4",
            "type": "labels",
            "value": {
              "start": 55,
              "end": 62,
              "text": "lucerna",
              "labels": [
                "object"
              ]
            },
            "from_name": "label",
            "to_name": "text",
            "origin": "prediction",
            "score": 0.9203017950057983
          },
          {
            "id": "a2f28105",
            "type": "labels",
            "value": {
              "start": 120,
              "end": 126,
              "text": "spinas",
              "labels": [
                "object"
              ]
            },
            "from_name": "label",
            "to_name": "text",
            "origin": "prediction",
            "score": 0.8459734320640564
          },
          {
            "id": "3cf1e01f",
            "type": "labels",
            "value": {
              "start": 107,
              "end": 113,
              "text": "lilium",
              "labels": [
                "object"
              ]
            },
            "from_name": "label",
            "to_name": "text",
            "origin": "prediction",
            "score": 0.8286247253417969
          },
          {
            "id": "4a6398d4",
            "type": "labels",
            "value": {
              "start": 183,
              "end": 191,
              "text": "calcaneo",
              "labels": [
                "object"
              ]
            },
            "from_name": "label",
            "to_name": "text",
            "origin": "prediction",
            "score": 0.8087706565856934
          },
          {
            "id": "8ddd4e87",
            "type": "labels",
            "value": {
              "start": 252,
              "end": 264,
              "text": "vase fictili",
              "labels": [
                "object"
              ]
            },
            "from_name": "label",
            "to_name": "text",
            "origin": "prediction",
            "score": 0.7801462411880493
          },
          {
            "id": "be728d2f",
            "type": "labels",
            "value": {
              "start": 869,
              "end": 873,
              "text": "dona",
              "labels": [
                "object"
              ]
            },
            "from_name": "label",
            "to_name": "text",
            "origin": "prediction",
            "score": 0.699946403503418
          },
          {
            "id": "de69624e",
            "type": "labels",
            "value": {
              "start": 1059,
              "end": 1070,
              "text": "ovina pelle",
              "labels": [
                "object"
              ]
            },
            "from_name": "label",
            "to_name": "text",
            "origin": "prediction",
            "score": 0.6479861736297607
          },
          {
            "id": "ba2671f9",
            "type": "labels",
            "value": {
              "start": 1220,
              "end": 1227,
              "text": "Christo",
              "labels": [
                "divine_entity"
              ]
            },
            "from_name": "label",
            "to_name": "text",
            "origin": "prediction",
            "score": 0.9980422258377075
          },
          {
            "id": "5936319f",
            "type": "labels",
            "value": {
              "start": 1414,
              "end": 1417,
              "text": "Deo",
              "labels": [
                "divine_entity"
              ]
            },
            "from_name": "label",
            "to_name": "text",
            "origin": "prediction",
            "score": 0.9976818561553955
          },
          {
            "id": "8439767f",
            "type": "labels",
            "value": {
              "start": 1524,
              "end": 1531,
              "text": "Dominum",
              "labels": [
                "divine_entity"
              ]
            },
            "from_name": "label",
            "to_name": "text",
            "origin": "prediction",
            "score": 0.9945138692855835
          },
          {
            "id": "a2ad68fa",
            "type": "labels",
            "value": {
              "start": 729,
              "end": 735,
              "text": "oppidi",
              "labels": [
                "place"
              ]
            },
            "from_name": "label",
            "to_name": "text",
            "origin": "prediction",
            "score": 0.9807928204536438
          },
          {
            "id": "ece8323d",
            "type": "labels",
            "value": {
              "start": 1362,
              "end": 1371,
              "text": "ecclesiam",
              "labels": [
                "institution"
              ]
            },
            "from_name": "label",
            "to_name": "text",
            "origin": "prediction",
            "score": 0.9901150465011597
          },
          {
            "id": "c130c9c1",
            "type": "labels",
            "value": {
              "start": 1019,
              "end": 1028,
              "text": "ecclesiam",
              "labels": [
                "institution"
              ]
            },
            "from_name": "label",
            "to_name": "text",
            "origin": "prediction",
            "score": 0.9883337020874023
          },
          {
            "id": "03abd230",
            "type": "labels",
            "value": {
              "start": 859,
              "end": 867,
              "text": "ecclesiæ",
              "labels": [
                "institution"
              ]
            },
            "from_name": "label",
            "to_name": "text",
            "origin": "prediction",
            "score": 0.9794437885284424
          }
        ]
      }
    ]
  },
  {
    "data": {
      "text": "[5]  Igitur nocte, qua rapienda erat, meruit angelicam vocem audire se monentem ex nomine: “Recede, inquiens, virgo, recede, et virginitatem, quam Deo consecrasti, inviolatam custodi.” Quæ valde perterrita, obediens jussioni, iter cepit. Cumque Spiritu Sancto duceretur, angelus Domini secundo ei apparuit et viam, quam ceperat, ne desereret imperavit. “Venies, inquit angelus, in villam, quam Meldricem nuncupabis; ibi namque præparavit tibi Deus locum ad perficiendum desiderii tui votum.” Pervenit igitur venerabilis virgo ad locum, quem prædixerat ei angelus; ibique parsimonia miræ abstinenciæ diu vivens, geminæ dilectionis se continebat mandato. Alebatur autem beata Ermelindis solummodo herbis agrestibus, non inferior summis heremi cultoribus: puellares quoque artus teneros duris cruciabat injuriis. Frequentabant quoque eam quique religiosi; sed quanto Dominus famam ejus dilatabat, tanto humilius se agebat. Tandem vero, post multa certamina evocata a Domino, ad cælestem pervenit gloriam; quam, in terris posita, tota devotione quæsivit. Ad cujus exequias non hominum \n\n[Col. 0850B] \n\nturba, sed ymnidici chori Christo cecinerunt gloriam. Et quia Christo fuit dilecta, ab ipsis est officiosissime sepulta. Hæc interea beata virgo quadraginta octo annis latuit aliena a cultu sæculi, solis venerata civibus cæli. Sic denique Christus manifestavit eam huic sæculo, ut, quæ erat jam apud eum glorificata in cælis, etiam apud homines honoraretur in terris."
    },
    "predictions": [
      {
        "model_version": "gliner2-multi-v1",
        "score": 0.9059909501591245,
        "result": [
          {
            "id": "4fc7d21b",
            "type": "labels",
            "value": {
              "start": 110,
              "end": 115,
              "text": "virgo",
              "labels": [
                "person"
              ]
            },
            "from_name": "label",
            "to_name": "text",
            "origin": "prediction",
            "score": 0.9879112243652344
          },
          {
            "id": "95194042",
            "type": "labels",
            "value": {
              "start": 1237,
              "end": 1242,
              "text": "virgo",
              "labels": [
                "person"
              ]
            },
            "from_name": "label",
            "to_name": "text",
            "origin": "prediction",
            "score": 0.9823161959648132
          },
          {
            "id": "332e96a2",
            "type": "labels",
            "value": {
              "start": 520,
              "end": 525,
              "text": "virgo",
              "labels": [
                "person"
              ]
            },
            "from_name": "label",
            "to_name": "text",
            "origin": "prediction",
            "score": 0.9818211197853088
          },
          {
            "id": "6827db13",
            "type": "labels",
            "value": {
              "start": 668,
              "end": 684,
              "text": "beata Ermelindis",
              "labels": [
                "person"
              ]
            },
            "from_name": "label",
            "to_name": "text",
            "origin": "prediction",
            "score": 0.908280611038208
          },
          {
            "id": "96ab3006",
            "type": "labels",
            "value": {
              "start": 394,
              "end": 403,
              "text": "Meldricem",
              "labels": [
                "person"
              ]
            },
            "from_name": "label",
            "to_name": "text",
            "origin": "prediction",
            "score": 0.7175852060317993
          },
          {
            "id": "e8ecd78f",
            "type": "labels",
            "value": {
              "start": 842,
              "end": 851,
              "text": "religiosi",
              "labels": [
                "group"
              ]
            },
            "from_name": "label",
            "to_name": "text",
            "origin": "prediction",
            "score": 0.9458149671554565
          },
          {
            "id": "4da0a175",
            "type": "labels",
            "value": {
              "start": 1098,
              "end": 1103,
              "text": "turba",
              "labels": [
                "group"
              ]
            },
            "from_name": "label",
            "to_name": "text",
            "origin": "prediction",
            "score": 0.9255344867706299
          },
          {
            "id": "33203575",
            "type": "labels",
            "value": {
              "start": 1311,
              "end": 1318,
              "text": "civibus",
              "labels": [
                "group"
              ]
            },
            "from_name": "label",
            "to_name": "text",
            "origin": "prediction",
            "score": 0.917891263961792
          },
          {
            "id": "2a3bc7dc",
            "type": "labels",
            "value": {
              "start": 1435,
              "end": 1442,
              "text": "homines",
              "labels": [
                "group"
              ]
            },
            "from_name": "label",
            "to_name": "text",
            "origin": "prediction",
            "score": 0.890808641910553
          },
          {
            "id": "5e4c74fa",
            "type": "labels",
            "value": {
              "start": 1073,
              "end": 1080,
              "text": "hominum",
              "labels": [
                "group"
              ]
            },
            "from_name": "label",
            "to_name": "text",
            "origin": "prediction",
            "score": 0.8834834098815918
          },
          {
            "id": "8bc77c70",
            "type": "labels",
            "value": {
              "start": 1109,
              "end": 1123,
              "text": "ymnidici chori",
              "labels": [
                "group"
              ]
            },
            "from_name": "label",
            "to_name": "text",
            "origin": "prediction",
            "score": 0.8765367865562439
          },
          {
            "id": "b2040174",
            "type": "labels",
            "value": {
              "start": 753,
              "end": 762,
              "text": "puellares",
              "labels": [
                "group"
              ]
            },
            "from_name": "label",
            "to_name": "text",
            "origin": "prediction",
            "score": 0.8000025153160095
          },
          {
            "id": "7002fb86",
            "type": "labels",
            "value": {
              "start": 702,
              "end": 712,
              "text": "agrestibus",
              "labels": [
                "group"
              ]
            },
            "from_name": "label",
            "to_name": "text",
            "origin": "prediction",
            "score": 0.6637303829193115
          },
          {
            "id": "10378e14",
            "type": "labels",
            "value": {
              "start": 734,
              "end": 751,
              "text": "heremi cultoribus",
              "labels": [
                "group"
              ]
            },
            "from_name": "label",
            "to_name": "text",
            "origin": "prediction",
            "score": 0.5254733562469482
          },
          {
            "id": "3d67e6df",
            "type": "labels",
            "value": {
              "start": 695,
              "end": 701,
              "text": "herbis",
              "labels": [
                "object"
              ]
            },
            "from_name": "label",
            "to_name": "text",
            "origin": "prediction",
            "score": 0.5705627202987671
          },
          {
            "id": "1c9c800f",
            "type": "labels",
            "value": {
              "start": 1337,
              "end": 1345,
              "text": "Christus",
              "labels": [
                "divine_entity"
              ]
            },
            "from_name": "label",
            "to_name": "text",
            "origin": "prediction",
            "score": 0.9932417273521423
          },
          {
            "id": "9d13ccae",
            "type": "labels",
            "value": {
              "start": 555,
              "end": 562,
              "text": "angelus",
              "labels": [
                "divine_entity"
              ]
            },
            "from_name": "label",
            "to_name": "text",
            "origin": "prediction",
            "score": 0.9920328259468079
          },
          {
            "id": "e37e19aa",
            "type": "labels",
            "value": {
              "start": 369,
              "end": 376,
              "text": "angelus",
              "labels": [
                "divine_entity"
              ]
            },
            "from_name": "label",
            "to_name": "text",
            "origin": "prediction",
            "score": 0.9918311238288879
          },
          {
            "id": "32afd562",
            "type": "labels",
            "value": {
              "start": 271,
              "end": 278,
              "text": "angelus",
              "labels": [
                "divine_entity"
              ]
            },
            "from_name": "label",
            "to_name": "text",
            "origin": "prediction",
            "score": 0.9894981384277344
          },
          {
            "id": "5f6770d1",
            "type": "labels",
            "value": {
              "start": 1124,
              "end": 1131,
              "text": "Christo",
              "labels": [
                "divine_entity"
              ]
            },
            "from_name": "label",
            "to_name": "text",
            "origin": "prediction",
            "score": 0.9880186319351196
          },
          {
            "id": "350a3080",
            "type": "labels",
            "value": {
              "start": 443,
              "end": 447,
              "text": "Deus",
              "labels": [
                "divine_entity"
              ]
            },
            "from_name": "label",
            "to_name": "text",
            "origin": "prediction",
            "score": 0.9878038167953491
          },
          {
            "id": "632fae00",
            "type": "labels",
            "value": {
              "start": 147,
              "end": 150,
              "text": "Deo",
              "labels": [
                "divine_entity"
              ]
            },
            "from_name": "label",
            "to_name": "text",
            "origin": "prediction",
            "score": 0.9839896559715271
          },
          {
            "id": "dbc1b26d",
            "type": "labels",
            "value": {
              "start": 1160,
              "end": 1167,
              "text": "Christo",
              "labels": [
                "divine_entity"
              ]
            },
            "from_name": "label",
            "to_name": "text",
            "origin": "prediction",
            "score": 0.9838922023773193
          },
          {
            "id": "ecfbfa41",
            "type": "labels",
            "value": {
              "start": 245,
              "end": 259,
              "text": "Spiritu Sancto",
              "labels": [
                "divine_entity"
              ]
            },
            "from_name": "label",
            "to_name": "text",
            "origin": "prediction",
            "score": 0.9809445142745972
          },
          {
            "id": "ac4ad81e",
            "type": "labels",
            "value": {
              "start": 964,
              "end": 970,
              "text": "Domino",
              "labels": [
                "divine_entity"
              ]
            },
            "from_name": "label",
            "to_name": "text",
            "origin": "prediction",
            "score": 0.9718634486198425
          },
          {
            "id": "f4fe5d41",
            "type": "labels",
            "value": {
              "start": 864,
              "end": 871,
              "text": "Dominus",
              "labels": [
                "divine_entity"
              ]
            },
            "from_name": "label",
            "to_name": "text",
            "origin": "prediction",
            "score": 0.9699713587760925
          },
          {
            "id": "c1355922",
            "type": "labels",
            "value": {
              "start": 279,
              "end": 285,
              "text": "Domini",
              "labels": [
                "divine_entity"
              ]
            },
            "from_name": "label",
            "to_name": "text",
            "origin": "prediction",
            "score": 0.8971278071403503
          },
          {
            "id": "034d5dfa",
            "type": "labels",
            "value": {
              "start": 45,
              "end": 60,
              "text": "angelicam vocem",
              "labels": [
                "divine_entity"
              ]
            },
            "from_name": "label",
            "to_name": "text",
            "origin": "prediction",
            "score": 0.8033123016357422
          },
          {
            "id": "fb82e215",
            "type": "labels",
            "value": {
              "start": 1458,
              "end": 1464,
              "text": "terris",
              "labels": [
                "place"
              ]
            },
            "from_name": "label",
            "to_name": "text",
            "origin": "prediction",
            "score": 0.9919008016586304
          },
          {
            "id": "fd9e70b6",
            "type": "labels",
            "value": {
              "start": 1011,
              "end": 1017,
              "text": "terris",
              "labels": [
                "place"
              ]
            },
            "from_name": "label",
            "to_name": "text",
            "origin": "prediction",
            "score": 0.9878502488136292
          },
          {
            "id": "c30248d2",
            "type": "labels",
            "value": {
              "start": 381,
              "end": 387,
              "text": "villam",
              "labels": [
                "place"
              ]
            },
            "from_name": "label",
            "to_name": "text",
            "origin": "prediction",
            "score": 0.9870275259017944
          },
          {
            "id": "ca595fc6",
            "type": "labels",
            "value": {
              "start": 529,
              "end": 534,
              "text": "locum",
              "labels": [
                "place"
              ]
            },
            "from_name": "label",
            "to_name": "text",
            "origin": "prediction",
            "score": 0.9788599014282227
          },
          {
            "id": "c6b393d7",
            "type": "labels",
            "value": {
              "start": 975,
              "end": 983,
              "text": "cælestem",
              "labels": [
                "place"
              ]
            },
            "from_name": "label",
            "to_name": "text",
            "origin": "prediction",
            "score": 0.9474691152572632
          },
          {
            "id": "51d885d0",
            "type": "labels",
            "value": {
              "start": 1417,
              "end": 1422,
              "text": "cælis",
              "labels": [
                "place"
              ]
            },
            "from_name": "label",
            "to_name": "text",
            "origin": "prediction",
            "score": 0.9419406652450562
          },
          {
            "id": "a0fac0c6",
            "type": "labels",
            "value": {
              "start": 448,
              "end": 453,
              "text": "locum",
              "labels": [
                "place"
              ]
            },
            "from_name": "label",
            "to_name": "text",
            "origin": "prediction",
            "score": 0.9398710131645203
          },
          {
            "id": "f46a49ce",
            "type": "labels",
            "value": {
              "start": 1319,
              "end": 1323,
              "text": "cæli",
              "labels": [
                "place"
              ]
            },
            "from_name": "label",
            "to_name": "text",
            "origin": "prediction",
            "score": 0.905167281627655
          },
          {
            "id": "c1f17cef",
            "type": "labels",
            "value": {
              "start": 734,
              "end": 740,
              "text": "heremi",
              "labels": [
                "place"
              ]
            },
            "from_name": "label",
            "to_name": "text",
            "origin": "prediction",
            "score": 0.7302981615066528
          }
        ]
      }
    ]
  },
  {
    "data": {
      "text": "[6]  Erat igitur homo quidam, qui præfatam solitudinem, ab angelo simul et beata Ermelinde Meldricem vocatam, cum transiret, contigit, Deo disponente, ut longius ire nequiret. Media autem noctis hora apparuit tumulus virginis, solis claritate lucidior, audivitque angelos psallentes. Apparente autem luce dici, disparuit visio cælestis, sed odor nimiæ suavitatis in eodem loco permansit. Post hæc prædictus vir devotus, peracto negotio, ad prædictum rediit locum, atque ad tumulum sui signi secundo devotissime excubavit; nec frustratus est spe sua. Nam pius Dominus iterum dignatus est illi revelare glorificationem sponsæ suæ. Quam enim apud se glorificaverat in cælis, disponebat et magnificare in terris. At ille, Domini voluntate \n\n[Col. 0850C] \n\ncertior effectus, surgens mane lætus, agensque Deo gratias, inquit: “Vere Dominus est in loco isto, et ego nesciebam”. Et statim reversus ad propria, omnibus quæ sui juris erant assumptis, super tumulum virginis cappellam fabricavit, ibique cum sobrietate vivens, finem dierum in pace sortitus est."
    },
    "predictions": [
      {
        "model_version": "gliner2-multi-v1",
        "score": 0.0,
        "result": []
      }
    ]
  },
  {
    "data": {
      "text": "[7]  Audientes igitur populi quod gestum erat, convenerunt ad locum, corde et animo concinentes hanc antiphonam: “Tua sunt hæc, Christe, opera, qui sanctos tuos ita glorificas, et cætera.” Statimque aperientes terram, apparuit sarcophagus, in quo jacebat inviolatæ virginis corpus. De subito tanta sanitatum emanavit copia, ut ei congruenter aptari posset, quod Dominus in Evangelio dicit: “Qui credit in me, opera quæ ego facio, et ipse faciet et majora faciet.” Nam cæcis visus, surdis auditus, claudis gressus, omnibus quoque pulsantibus salus et incolumitas reddebatur. Dæmones etiam ex obsessis corporibus egredientes, expulsione \n\n[Col. 0850D] \n\nsua meritum virginis inviti prodebant. Denique quicunque sepulcrum ejus fideliter tetigisset, sanus fiebat, a quacumque detinebatur infirmitate. Odore virtutum ejus commoti, ex longinquis regionibus superveniebant viri cum mulieribus, et virgines delicatæ, nudis pedibus misericordiam Domini implorantes. Per meritum autem beatæ virginis Ermelindis gratiam Dei sibi adfuisse sentiebant, læti et alacres remeantes ad propria. Amen."
    },
    "predictions": [
      {
        "model_version": "gliner2-multi-v1",
        "score": 0.8930818510055542,
        "result": [
          {
            "id": "ff85cc34",
            "type": "labels",
            "value": {
              "start": 981,
              "end": 989,
              "text": "virginis",
              "labels": [
                "person"
              ]
            },
            "from_name": "label",
            "to_name": "text",
            "origin": "prediction",
            "score": 0.9542658925056458
          },
          {
            "id": "52d98c7e",
            "type": "labels",
            "value": {
              "start": 664,
              "end": 672,
              "text": "virginis",
              "labels": [
                "person"
              ]
            },
            "from_name": "label",
            "to_name": "text",
            "origin": "prediction",
            "score": 0.9494622349739075
          },
          {
            "id": "a11a2406",
            "type": "labels",
            "value": {
              "start": 265,
              "end": 273,
              "text": "virginis",
              "labels": [
                "person"
              ]
            },
            "from_name": "label",
            "to_name": "text",
            "origin": "prediction",
            "score": 0.9394121170043945
          },
          {
            "id": "cbe23da1",
            "type": "labels",
            "value": {
              "start": 22,
              "end": 28,
              "text": "populi",
              "labels": [
                "group"
              ]
            },
            "from_name": "label",
            "to_name": "text",
            "origin": "prediction",
            "score": 0.9726517796516418
          },
          {
            "id": "e884cf7f",
            "type": "labels",
            "value": {
              "start": 866,
              "end": 870,
              "text": "viri",
              "labels": [
                "group"
              ]
            },
            "from_name": "label",
            "to_name": "text",
            "origin": "prediction",
            "score": 0.9260314702987671
          },
          {
            "id": "68380083",
            "type": "labels",
            "value": {
              "start": 514,
              "end": 521,
              "text": "omnibus",
              "labels": [
                "group"
              ]
            },
            "from_name": "label",
            "to_name": "text",
            "origin": "prediction",
            "score": 0.8630250692367554
          },
          {
            "id": "854b9f21",
            "type": "labels",
            "value": {
              "start": 468,
              "end": 473,
              "text": "cæcis",
              "labels": [
                "group"
              ]
            },
            "from_name": "label",
            "to_name": "text",
            "origin": "prediction",
            "score": 0.7824286818504333
          },
          {
            "id": "5ff0c585",
            "type": "labels",
            "value": {
              "start": 890,
              "end": 898,
              "text": "virgines",
              "labels": [
                "group"
              ]
            },
            "from_name": "label",
            "to_name": "text",
            "origin": "prediction",
            "score": 0.7774465680122375
          },
          {
            "id": "be7ffeec",
            "type": "labels",
            "value": {
              "start": 875,
              "end": 885,
              "text": "mulieribus",
              "labels": [
                "group"
              ]
            },
            "from_name": "label",
            "to_name": "text",
            "origin": "prediction",
            "score": 0.7631152272224426
          },
          {
            "id": "fe60a89a",
            "type": "labels",
            "value": {
              "start": 148,
              "end": 155,
              "text": "sanctos",
              "labels": [
                "group"
              ]
            },
            "from_name": "label",
            "to_name": "text",
            "origin": "prediction",
            "score": 0.6713287234306335
          },
          {
            "id": "7ed8e8ee",
            "type": "labels",
            "value": {
              "start": 481,
              "end": 487,
              "text": "surdis",
              "labels": [
                "group"
              ]
            },
            "from_name": "label",
            "to_name": "text",
            "origin": "prediction",
            "score": 0.6629165410995483
          },
          {
            "id": "964f4d38",
            "type": "labels",
            "value": {
              "start": 274,
              "end": 280,
              "text": "corpus",
              "labels": [
                "object"
              ]
            },
            "from_name": "label",
            "to_name": "text",
            "origin": "prediction",
            "score": 0.9476980566978455
          },
          {
            "id": "017c0c53",
            "type": "labels",
            "value": {
              "start": 600,
              "end": 610,
              "text": "corporibus",
              "labels": [
                "object"
              ]
            },
            "from_name": "label",
            "to_name": "text",
            "origin": "prediction",
            "score": 0.9336813688278198
          },
          {
            "id": "00a8c935",
            "type": "labels",
            "value": {
              "start": 101,
              "end": 111,
              "text": "antiphonam",
              "labels": [
                "object"
              ]
            },
            "from_name": "label",
            "to_name": "text",
            "origin": "prediction",
            "score": 0.8735294342041016
          },
          {
            "id": "49595716",
            "type": "labels",
            "value": {
              "start": 574,
              "end": 581,
              "text": "Dæmones",
              "labels": [
                "divine_entity"
              ]
            },
            "from_name": "label",
            "to_name": "text",
            "origin": "prediction",
            "score": 0.9957095384597778
          },
          {
            "id": "a3d8751b",
            "type": "labels",
            "value": {
              "start": 937,
              "end": 943,
              "text": "Domini",
              "labels": [
                "divine_entity"
              ]
            },
            "from_name": "label",
            "to_name": "text",
            "origin": "prediction",
            "score": 0.9954257607460022
          },
          {
            "id": "513ceab2",
            "type": "labels",
            "value": {
              "start": 1009,
              "end": 1012,
              "text": "Dei",
              "labels": [
                "divine_entity"
              ]
            },
            "from_name": "label",
            "to_name": "text",
            "origin": "prediction",
            "score": 0.9933191537857056
          },
          {
            "id": "a2cc90c6",
            "type": "labels",
            "value": {
              "start": 362,
              "end": 369,
              "text": "Dominus",
              "labels": [
                "divine_entity"
              ]
            },
            "from_name": "label",
            "to_name": "text",
            "origin": "prediction",
            "score": 0.9929360747337341
          },
          {
            "id": "d252393b",
            "type": "labels",
            "value": {
              "start": 128,
              "end": 135,
              "text": "Christe",
              "labels": [
                "divine_entity"
              ]
            },
            "from_name": "label",
            "to_name": "text",
            "origin": "prediction",
            "score": 0.9885333776473999
          },
          {
            "id": "29f4c714",
            "type": "labels",
            "value": {
              "start": 210,
              "end": 216,
              "text": "terram",
              "labels": [
                "place"
              ]
            },
            "from_name": "label",
            "to_name": "text",
            "origin": "prediction",
            "score": 0.9776520133018494
          },
          {
            "id": "83284cea",
            "type": "labels",
            "value": {
              "start": 62,
              "end": 67,
              "text": "locum",
              "labels": [
                "place"
              ]
            },
            "from_name": "label",
            "to_name": "text",
            "origin": "prediction",
            "score": 0.9743492007255554
          },
          {
            "id": "683d6449",
            "type": "labels",
            "value": {
              "start": 709,
              "end": 718,
              "text": "sepulcrum",
              "labels": [
                "place"
              ]
            },
            "from_name": "label",
            "to_name": "text",
            "origin": "prediction",
            "score": 0.9490981698036194
          },
          {
            "id": "8eae8ecd",
            "type": "labels",
            "value": {
              "start": 227,
              "end": 238,
              "text": "sarcophagus",
              "labels": [
                "place"
              ]
            },
            "from_name": "label",
            "to_name": "text",
            "origin": "prediction",
            "score": 0.9259725213050842
          },
          {
            "id": "6a7f5368",
            "type": "labels",
            "value": {
              "start": 840,
              "end": 850,
              "text": "regionibus",
              "labels": [
                "place"
              ]
            },
            "from_name": "label",
            "to_name": "text",
            "origin": "prediction",
            "score": 0.7924898266792297
          },
          {
            "id": "e731f05c",
            "type": "labels",
            "value": {
              "start": 373,
              "end": 382,
              "text": "Evangelio",
              "labels": [
                "text_title"
              ]
            },
            "from_name": "label",
            "to_name": "text",
            "origin": "prediction",
            "score": 0.7245674729347229
          }
        ]
      }
    ]
  }
]